cartagen4py/__init__.py
cartagen4py/_version.py
cartagen4py/algorithms/__init__.py
cartagen4py/algorithms/buildings/__init__.py
cartagen4py/algorithms/buildings/amalgamation.py
cartagen4py/algorithms/buildings/displacement.py
cartagen4py/algorithms/buildings/regularization.py
cartagen4py/algorithms/buildings/simplification.py
cartagen4py/algorithms/buildings/squaring.py
cartagen4py/algorithms/general/__init__.py
cartagen4py/algorithms/general/constraint.py
cartagen4py/algorithms/lines/__init__.py
cartagen4py/algorithms/lines/bends.py
cartagen4py/algorithms/lines/breaks.py
cartagen4py/algorithms/network/__init__.py
cartagen4py/algorithms/network/branching_crossroads.py
cartagen4py/algorithms/network/dead_ends.py
cartagen4py/algorithms/network/dual_carriageways.py
cartagen4py/algorithms/network/roundabouts.py
cartagen4py/algorithms/points/__init__.py
cartagen4py/algorithms/points/covering.py
cartagen4py/algorithms/points/label_grid_oop.py
cartagen4py/algorithms/points/quadtree.py
cartagen4py/algorithms/points/reduction.py
cartagen4py/algorithms/points/swinging_arm.py
cartagen4py/data/__init__.py
cartagen4py/enrichment/__init__.py
cartagen4py/enrichment/building_measures.py
cartagen4py/enrichment/pastiness.py
cartagen4py/enrichment/strokes.py
cartagen4py/enrichment/strokes_river.py
cartagen4py/enrichment/urban_areas.py
cartagen4py/enrichment/network/__init__.py
cartagen4py/enrichment/network/branching_crossroads.py
cartagen4py/enrichment/network/dead_ends.py
cartagen4py/enrichment/network/dual_carriageways.py
cartagen4py/enrichment/network/roundabouts.py
cartagen4py/enrichment/network/rural_areas.py
cartagen4py/evaluation/__init__.py
cartagen4py/evaluation/constraint_satisfaction.py
cartagen4py/evaluation/constraint_monitors/__init__.py
cartagen4py/evaluation/constraint_monitors/building_size_monitor.py
cartagen4py/evaluation/constraint_monitors/constraint_monitor.py
cartagen4py/evaluation/constraint_monitors/object_granularity_monitor.py
cartagen4py-0.4.0.dist-info/LICENSE.md
cartagen4py-0.4.0.dist-info/METADATA
cartagen4py-0.4.0.dist-info/WHEEL
cartagen4py-0.4.0.dist-info/top_level.txt
cartagen4py-0.4.0.dist-info/RECORD
