Metadata-Version: 2.1
Name: cartagen4py
Version: 0.4.0
Summary: Cartographic generalisation of spatial objects
Home-page: https://github.com/LostInZoom/cartagen4py
Author: 
Requires-Dist: setuptools
